yaml2html/__init__.py
yaml_to_html-0.0.1a1.dist-info/LICENSE
yaml_to_html-0.0.1a1.dist-info/METADATA
yaml_to_html-0.0.1a1.dist-info/WHEEL
yaml_to_html-0.0.1a1.dist-info/RECORD
