Metadata-Version: 2.1
Name: yaml-to-html
Version: 0.0.1a1
Summary: Write HTML in YAML!
Author: Anirudh Dutt
Author-email: 1468519+aneroid@users.noreply.github.com
Requires-Python: >=3.8,<4.0
Classifier: Programming Language :: Python :: 3
Classifier: Programming Language :: Python :: 3.8
Classifier: Programming Language :: Python :: 3.9
Classifier: Programming Language :: Python :: 3.10
Classifier: Programming Language :: Python :: 3.11
Classifier: Programming Language :: Python :: 3.12
Requires-Dist: beautifulsoup4 (>=4,<5)
Requires-Dist: pyyaml (>=6,<7)
